{
    "job_id": "4137530712",
    "title": "Business Analyst",
    "company": "Newton School",
    "location": "Bengaluru, Karnataka, India",
    "description": "Responsibilities\n\n\nYou need to be a big-picture problem solver and a strategic partner.\nYou also need to demonstrate analytical thinking through data-driven decisions and possess the technical know-how, fascination, and team spirit to make a huge impact.\nThe team member is expected to clean, analyze, and visualize student data.\nWork with large, complex data sets to solve difficult, non-routine analysis problems.\nBuild data pipelines and dashboards to self-serve data needs.\nSupport senior leadership on business decisions through insights derived from data.\n\n\nRequirements\n\n\n1-2 Years of relevant experience in a business analytics role.\nHigh proficiency in advanced Excel and SQL.\nProficiency in Python, PowerBI, VBA, and Tableau is preferred.\nGood problem-solving and insight-generation skills.\nExcellent communication skills with technical and non-technical stakeholders.\nBachelor's degree is compulsory.\n\n\nThis job was posted by Tarandeep Kaur from Newton School.\nShow more ",
    "link": "https://in.linkedin.com/jobs/view/business-analyst-at-newton-school-4137530712?position=10&pageNum=77&refId=x7m7XCf9mecSRbX%2FzrmwDg%3D%3D&trackingId=JqQv7136kcqqbocH09%2Fb6Q%3D%3D"
}