{
    "job_id": "4141923280",
    "title": "Business Analyst",
    "company": "Tata Consultancy Services",
    "location": "Kolkata, West Bengal, India",
    "description": "Greetings from TCS,\n\n\n\n\nTCS Kolkata providing excellent opportunity for Business Analyst (Life Insurance) on 6th Feb(Thursday) through virtual mode !!!!\n\n\n\n\nJob Title :- Business Analyst Life Insurance\n\nJob Location: Kolkata\n\nExperience Range: 8 to 12 Years\n\n\n\n\nMust Have:\n\n\n\n\nStrong knowledge in Life Insurance Domain\nExceptional analytical and conceptual thinking skills.\nThe ability to influence stakeholders and work closely with them to determine acceptable solutions.\nUnderstand the requirement and create documents\nFundamental analytical and conceptual thinking skills.\nCompetency in Microsoft applications including Word, Excel, and Outlook. A history of leading and supporting successful projects.\n\nResponsibilities:\n\n\n\n\nEvaluating business processes, anticipating requirements, uncovering areas for improvement, and developing and implementing solutions.\nLeading ongoing reviews of business processes and developing optimization strategies.\nConducting meetings and presentations to share ideas and findings.\nPerforming requirements analysis.\nDocumenting and communicating the results of your efforts.\nEffectively communicating your insights and plans to cross-functional team members and management.\nGathering critical information from meetings with various stakeholders and producing useful reports.\nWorking closely with clients, technicians, and managerial staff.\nEnsuring solutions meet business needs and requirements.\nPerforming user acceptance testing.\nMonitoring deliverables and ensuring timely completion of projects\n\nShow more ",
    "link": "https://in.linkedin.com/jobs/view/business-analyst-at-tata-consultancy-services-4141923280?position=37&pageNum=0&refId=QqFlOKlrnyFKzly5T4N%2BOA%3D%3D&trackingId=fkR6l8xcFcNWmNVzTGcQUg%3D%3D"
}