{
    "job_id": "4146038716",
    "title": "Lead Business Analyst",
    "company": "EPAM Systems",
    "location": "Chennai, Tamil Nadu, India",
    "description": "We are looking for a highly skilled Lead Business Analyst with 10-12 years of experience in business analysis and product ownership. This role requires hands-on experience with market-leading CRMs, ERPs, UI/UX design, data management, and AI-driven solutions.\n\nResponsibilities\n\n\n\nLead business analysis activities, ensuring alignment with business objectives and stakeholder expectations\nCollaborate with cross-functional teams, including product owners, developers, and UX/UI designers, to deliver high-quality solutions\nDesign and document business requirements, workflows, and user stories\nWork closely with Agile teams to implement Scrum, Kanban, and SAFe methodologies\nConduct market research and competitive analysis to identify industry trends and opportunities\nDrive the adoption of AI models to enhance productivity in business analysis and product ownership activities\nOversee data management, ETL processes, and API integrations\nDevelop mock-ups and wireframes to support UI/UX design efforts\nFacilitate workshops, sprint planning, and retrospectives to ensure continuous improvement\n\n\n\nRequirements\n\n\n\n10+ years of experience in business analysis and product ownership\nExpertise in BFSI, Healthcare, Insurance, and Lifesciences, with the ability to adapt to new domains\nHands-on experience with market-leading CRMs and ERPs\nStrong knowledge of UI/UX design and mock-ups\nProficiency in Agile frameworks, including Scrum, Kanban, and SAFe\nExperience working with data management, ETL processes, and APIs\nProven track record of implementing AI models to enhance productivity in business analysis and product ownership\nExperience in AI solutioning as a business analyst or product owner\nExcellent communication, stakeholder management, and problem-solving skills\nEnglish level B2+\n\n\n\nShow more ",
    "link": "https://in.linkedin.com/jobs/view/lead-business-analyst-at-epam-systems-4146038716?position=6&pageNum=45&refId=UbUFWb7IHPllL5XcmhINQg%3D%3D&trackingId=nxFgp4oDVQgl9p4AJlRXlA%3D%3D"
}